pysm3/__init__.py
pysm3/_version.py
pysm3/distribution.py
pysm3/mpi.py
pysm3/sky.py
pysm3/units.py
pysm3/data/README.rst
pysm3/data/__init__.py
pysm3/data/presets.cfg
pysm3/extern/__init__.py
pysm3/models/__init__.py
pysm3/models/catalog.py
pysm3/models/cmb.py
pysm3/models/co_lines.py
pysm3/models/dipole.py
pysm3/models/dust.py
pysm3/models/dust_layers.py
pysm3/models/dust_realization.py
pysm3/models/hd2017.py
pysm3/models/interpolating.py
pysm3/models/power_law.py
pysm3/models/power_law_realization.py
pysm3/models/spdust.py
pysm3/models/template.py
pysm3/models/websky.py
pysm3/utils/__init__.py
pysm3/utils/add_metadata.py
pysm3/utils/data.py
pysm3/utils/exceptions.py
pysm3/utils/logpoltens.py
pysm3/utils/photometry.py
pysm3/utils/small_scales.py
pysm3/utils/spherical_harmonics.py
pysm3/utils/tests/__init__.py
pysm3-3.4.3.dist-info/METADATA
pysm3-3.4.3.dist-info/WHEEL
pysm3-3.4.3.dist-info/licenses/LICENSE
pysm3-3.4.3.dist-info/RECORD
