Metadata-Version: 2.4
Name: pysm3
Version: 3.4.3
Summary: PySM generates full-sky simulations of Galactic emissions in intensity and polarization
Project-URL: Homepage, https://github.com/galsci/pysm
Project-URL: Documentation, https://pysm3.readthedocs.io/
Project-URL: Bug Tracker, https://github.com/galsci/pysm/issues
Project-URL: Changelog, https://github.com/galsci/pysm/blob/main/CHANGES.rst
Author-email: Andrea Zonca <code@andreazonca.com>
License: Copyright 2021 Andrea Zonca
License-File: LICENSE
Classifier: Development Status :: 4 - Beta
Classifier: License :: OSI Approved :: BSD License
Classifier: Programming Language :: Python :: 3 :: Only
Classifier: Programming Language :: Python :: 3.8
Classifier: Programming Language :: Python :: 3.9
Classifier: Programming Language :: Python :: 3.10
Classifier: Programming Language :: Python :: 3.11
Classifier: Programming Language :: Python :: 3.12
Classifier: Programming Language :: Python :: 3.13
Classifier: Topic :: Scientific/Engineering :: Physics
Requires-Python: >=3.9
Requires-Dist: astropy
Requires-Dist: h5py
Requires-Dist: healpy>=1.16.0
Requires-Dist: importlib-metadata; python_version < '3.8'
Requires-Dist: numba
Requires-Dist: numpy<2
Requires-Dist: scipy<1.15
Requires-Dist: toml
Provides-Extra: docs
Requires-Dist: ipykernel; extra == 'docs'
Requires-Dist: nbsphinx; extra == 'docs'
Requires-Dist: pandoc; extra == 'docs'
Requires-Dist: sphinx-astropy; extra == 'docs'
Requires-Dist: sphinx-math-dollar; extra == 'docs'
Requires-Dist: sphinx-pyproject; extra == 'docs'
Provides-Extra: mpi
Requires-Dist: mpi4py; extra == 'mpi'
Provides-Extra: test
Requires-Dist: ipykernel; extra == 'test'
Requires-Dist: nbval; extra == 'test'
Requires-Dist: netcdf4; extra == 'test'
Requires-Dist: pixell==0.26.0; extra == 'test'
Requires-Dist: psutil; extra == 'test'
Requires-Dist: pytest; extra == 'test'
Requires-Dist: pytest-astropy; extra == 'test'
Requires-Dist: tox; extra == 'test'
Requires-Dist: xarray; extra == 'test'
